README.rst
setup.cfg
setup.py
Flask_Gladiator.egg-info/PKG-INFO
Flask_Gladiator.egg-info/SOURCES.txt
Flask_Gladiator.egg-info/dependency_links.txt
Flask_Gladiator.egg-info/not-zip-safe
Flask_Gladiator.egg-info/requires.txt
Flask_Gladiator.egg-info/top_level.txt
flask_gladiator/__init__.py