Metadata-Version: 1.1
Name: Flask-Gladiator
Version: 0.1
Summary: Gladiator is a Data Validation Framework for Python3 (Flask Plugin)
Home-page: https://github.com/laco/flask-gladiator
Author: László Andrási
Author-email: mail@laszloandrasi.com
License: BSD
Download-URL: https://github.com/laco/flask-gladiator/tarball/0.1
Platform: any
Classifier: Development Status :: 4 - Beta
Classifier: Environment :: Web Environment
Classifier: Intended Audience :: Developers
Classifier: License :: OSI Approved :: BSD License
Classifier: Operating System :: OS Independent
Classifier: Programming Language :: Python
Classifier: Programming Language :: Python :: 3
Classifier: Topic :: Internet :: WWW/HTTP :: Dynamic Content
Classifier: Topic :: Software Development :: Libraries :: Python Modules
